{"cameraMode":{"drawMode":0,"name":"Shaded","section":"Shading Mode"},"sceneLighting":true,"audioPlay":false,"sceneViewState":{"m_AlwaysRefresh":false,"showFog":true,"showSkybox":true,"showFlares":true,"showImageEffects":true,"showParticleSystems":true,"showVisualEffectGraphs":true,"m_FxEnabled":true},"in2DMode":false,"pivot":{"x":416.9779052734375,"y":261.84405517578127,"z":9.578829765319825},"rotation":{"x":-0.0009017685079015791,"y":-0.9978626370429993,"z":0.013781142421066761,"w":-0.06484577804803848},"size":17.927881240844728,"orthographic":false}